Metadata-Version: 2.1
Name: pyramid-route-7
Version: 0.4.0
Summary: micro-templating extensions to Pyramid routing
Home-page: https://github.com/jvanasco/pyramid_route_7
Author: Jonathan Vanasco
Author-email: jonathan@findmeon.com
License: MIT
Keywords: web pyramid routing routes
Classifier: Intended Audience :: Developers
Classifier: Framework :: Pyramid
Classifier: Programming Language :: Python :: 3
Classifier: Programming Language :: Python :: 3.6
Classifier: Programming Language :: Python :: 3.7
Classifier: Programming Language :: Python :: 3.8
Classifier: Programming Language :: Python :: 3.9
Classifier: Programming Language :: Python :: 3.10
Classifier: Programming Language :: Python :: 3.11
Classifier: License :: OSI Approved :: MIT License
Provides-Extra: testing
License-File: LICENSE.txt
